{
   "data": [
        {
            "bonus_amount" : "33.00",
            "bonus_id" : 52,
            "bonus_name" : "\U5546\U54c1\U7ea2\U5305",
            "end_date" : 1490141094,
            "formatted_bonus_amount" : "\U00a533.00",
            "formatted_end_date" : "2017-03-22",
            "formatted_request_amount" : "\U00a533.01",
            "formatted_start_date" : "2017-02-22",
            "label_status" : "\U53ef\U4f7f\U7528",
            "request_amount" : "33.01",
            "start_date" : 1487721894,
            "status" : "allow_use"
        },
        {
            "bonus_amount" : "33.00",
            "bonus_id" : 52,
            "bonus_name" : "\U5546\U54c1\U7ea2\U5305",
            "end_date" : 1490141094,
            "formatted_bonus_amount" : "\U00a533.00",
            "formatted_end_date" : "2017-03-22",
            "formatted_request_amount" : "\U00a533.01",
            "formatted_start_date" : "2017-02-22",
            "label_status" : "\U53ef\U4f7f\U7528",
            "request_amount" : "33.01",
            "start_date" : 1487721894,
            "status" : "allow_use"
        },
        {
            "bonus_amount" : "33.00",
            "bonus_id" : 52,
            "bonus_name" : "\U5546\U54c1\U7ea2\U5305",
            "end_date" : 1490141094,
            "formatted_bonus_amount" : "\U00a533.00",
            "formatted_end_date" : "2017-03-22",
            "formatted_request_amount" : "\U00a533.01",
            "formatted_start_date" : "2017-02-22",
            "label_status" : "\U53ef\U4f7f\U7528",
            "request_amount" : "33.01",
            "start_date" : 1487721894,
            "status" : "allow_use"
        },
        {
            "bonus_amount" : "33.00",
            "bonus_id" : 52,
            "bonus_name" : "\U5546\U54c1\U7ea2\U5305",
            "end_date" : 1490141094,
            "formatted_bonus_amount" : "\U00a533.00",
            "formatted_end_date" : "2017-03-22",
            "formatted_request_amount" : "\U00a533.01",
            "formatted_start_date" : "2017-02-22",
            "label_status" : "\U53ef\U4f7f\U7528",
            "request_amount" : "33.01",
            "start_date" : 1487721894,
            "status" : "allow_use"
        }
   ],
   "status": {
        "succeed": 1
    }
}